skylab_studio/__init__.py
skylab_studio/version.py
skylab_studio-1.0.0.dist-info/LICENSE
skylab_studio-1.0.0.dist-info/METADATA
skylab_studio-1.0.0.dist-info/WHEEL
skylab_studio-1.0.0.dist-info/top_level.txt
skylab_studio-1.0.0.dist-info/RECORD
